{
    "openapi": "3.0.0",
    "info": {
        "title": "Deni",
        "description": "Descripción de la API de Ejemplo",
        "termsOfService": "https://www.ejemplo.com/terms",
        "contact": {
            "email": "contacto@ejemplo.com"
        },
        "license": {
            "name": "Licencia de Ejemplo",
            "url": "https://www.ejemplo.com/licencia"
        },
        "version": "1.0"
    },
    "paths": {
        "/adoptantes": {
            "get": {
                "tags": [
                    "Adoptantes"
                ],
                "summary": "Obtener todos los adoptantes",
                "description": "Recupera todos los adoptantes de la base de datos.",
                "operationId": "getAll",
                "responses": {
                    "200": {
                        "description": "Lista de adoptantes",
                        "content": {
                            "application/json": {
                                "schema": {
                                    "type": "array",
                                    "items": {
                                        "$ref": "#/components/schemas/adoptante"
                                    }
                                }
                            }
                        }
                    }
                }
            },
            "post": {
                "tags": [
                    "Adoptantes"
                ],
                "summary": "Registrar un nuevo adoptante",
                "description": "Crear un nuevo adoptante con la información proporcionada.",
                "operationId": "store",
                "requestBody": {
                    "description": "Datos del adoptante",
                    "required": true,
                    "content": {
                        "application/json": {
                            "schema": {
                                "required": [
                                    "nombre",
                                    "apellido",
                                    "correo_electronico",
                                    "telefono",
                                    "direccion"
                                ],
                                "properties": {
                                    "nombre": {
                                        "type": "string",
                                        "format": "string",
                                        "example": "Nombre"
                                    },
                                    "apellido": {
                                        "type": "string",
                                        "format": "string",
                                        "example": "Apellido"
                                    },
                                    "correo_electronico": {
                                        "type": "string",
                                        "format": "email",
                                        "example": "adoptante@ejemplo.com"
                                    },
                                    "telefono": {
                                        "type": "string",
                                        "format": "string",
                                        "example": "123456789"
                                    },
                                    "direccion": {
                                        "type": "string",
                                        "format": "string",
                                        "example": "Dirección de ejemplo"
                                    },
                                    "ocupacion": {
                                        "type": "string",
                                        "format": "string",
                                        "example": "Ocupación de ejemplo"
                                    }
                                },
                                "type": "object"
                            }
                        }
                    }
                },
                "responses": {
                    "201": {
                        "description": "Adoptante registrado exitosamente",
                        "content": {
                            "application/json": {
                                "schema": {
                                    "$ref": "#/components/schemas/adoptante"
                                }
                            }
                        }
                    },
                    "422": {
                        "description": "Validación fallida",
                        "content": {
                            "application/json": {
                                "schema": {
                                    "properties": {
                                        "error": {
                                            "type": "string",
                                            "example": "Error de validación"
                                        },
                                        "errors": {
                                            "type": "object"
                                        }
                                    },
                                    "type": "object"
                                }
                            }
                        }
                    }
                }
            }
        },
        "/adoptantes/{id}": {
            "get": {
                "tags": [
                    "Adoptantes"
                ],
                "summary": "Obtener información de un adoptante",
                "description": "Obtiene información de un adoptante por su ID.",
                "operationId": "show",
                "parameters": [
                    {
                        "name": "id",
                        "in": "path",
                        "description": "ID del adoptante",
                        "required": true,
                        "schema": {
                            "type": "integer"
                        }
                    }
                ],
                "responses": {
                    "200": {
                        "description": "Información del adoptante",
                        "content": {
                            "application/json": {
                                "schema": {
                                    "$ref": "#/components/schemas/adoptante"
                                }
                            }
                        }
                    },
                    "404": {
                        "description": "Adoptante no encontrado",
                        "content": {
                            "application/json": {
                                "schema": {
                                    "properties": {
                                        "error": {
                                            "type": "string",
                                            "example": "Adoptante no encontrado"
                                        }
                                    },
                                    "type": "object"
                                }
                            }
                        }
                    }
                }
            }
        },
        "/adoptantes/{ci}": {
            "get": {
                "tags": [
                    "Adoptantes"
                ],
                "summary": "Obtener información de un adoptante por CI",
                "description": "Obtiene información de un adoptante por su CI.",
                "operationId": "showByCI",
                "parameters": [
                    {
                        "name": "ci",
                        "in": "path",
                        "description": "Cédula de identidad del adoptante",
                        "required": true,
                        "schema": {
                            "type": "string"
                        }
                    }
                ],
                "responses": {
                    "200": {
                        "description": "Información del adoptante",
                        "content": {
                            "application/json": {
                                "schema": {
                                    "$ref": "#/components/schemas/adoptante"
                                }
                            }
                        }
                    },
                    "404": {
                        "description": "Adoptante no encontrado",
                        "content": {
                            "application/json": {
                                "schema": {
                                    "properties": {
                                        "error": {
                                            "type": "string",
                                            "example": "Adoptante no encontrado"
                                        }
                                    },
                                    "type": "object"
                                }
                            }
                        }
                    }
                }
            }
        },
        "/animales": {
            "get": {
                "tags": [
                    "Animales"
                ],
                "summary": "Obtener todos los animales",
                "description": "Recupera todos los animales de la base de datos.",
                "operationId": "indexAnimales",
                "responses": {
                    "200": {
                        "description": "Lista de animales",
                        "content": {
                            "application/json": {
                                "schema": {
                                    "type": "array",
                                    "items": {
                                        "$ref": "#/components/schemas/animal"
                                    }
                                }
                            }
                        }
                    }
                }
            },
            "post": {
                "tags": [
                    "Animales"
                ],
                "summary": "Registrar un nuevo animal",
                "description": "Crear un nuevo animal con la información proporcionada.",
                "operationId": "storeAnimal",
                "requestBody": {
                    "description": "Datos del animal",
                    "required": true,
                    "content": {
                        "application/json": {
                            "schema": {
                                "required": [
                                    "nombre",
                                    "especie"
                                ],
                                "properties": {
                                    "nombre": {
                                        "type": "string",
                                        "format": "string",
                                        "example": "Nombre"
                                    },
                                    "especie": {
                                        "type": "string",
                                        "format": "string",
                                        "example": "Especie"
                                    },
                                    "raza": {
                                        "type": "string",
                                        "format": "string",
                                        "example": "Raza"
                                    },
                                    "edad": {
                                        "type": "integer",
                                        "format": "int",
                                        "example": 3
                                    },
                                    "descripcion": {
                                        "type": "string",
                                        "format": "string",
                                        "example": "Descripción del animal"
                                    }
                                },
                                "type": "object"
                            }
                        }
                    }
                },
                "responses": {
                    "201": {
                        "description": "Animal registrado exitosamente",
                        "content": {
                            "application/json": {
                                "schema": {
                                    "$ref": "#/components/schemas/animal"
                                }
                            }
                        }
                    },
                    "422": {
                        "description": "Validación fallida",
                        "content": {
                            "application/json": {
                                "schema": {
                                    "properties": {
                                        "error": {
                                            "type": "string",
                                            "example": "Error de validación"
                                        },
                                        "errors": {
                                            "type": "object"
                                        }
                                    },
                                    "type": "object"
                                }
                            }
                        }
                    }
                }
            }
        },
        "/animales/{id}": {
            "get": {
                "tags": [
                    "Animales"
                ],
                "summary": "Obtener información de un animal",
                "description": "Obtiene información de un animal por su ID.",
                "operationId": "showAnimal",
                "parameters": [
                    {
                        "name": "id",
                        "in": "path",
                        "description": "ID del animal",
                        "required": true,
                        "schema": {
                            "type": "integer"
                        }
                    }
                ],
                "responses": {
                    "200": {
                        "description": "Información del animal",
                        "content": {
                            "application/json": {
                                "schema": {
                                    "$ref": "#/components/schemas/animal"
                                }
                            }
                        }
                    },
                    "404": {
                        "description": "Animal no encontrado",
                        "content": {
                            "application/json": {
                                "schema": {
                                    "properties": {
                                        "error": {
                                            "type": "string",
                                            "example": "Animal no encontrado"
                                        }
                                    },
                                    "type": "object"
                                }
                            }
                        }
                    }
                }
            }
        },
        "/generar-pdf-animales": {
            "get": {
                "tags": [
                    "Animales"
                ],
                "summary": "Generar PDF de animales",
                "description": "Genera un archivo PDF que contiene la lista de todos los animales.",
                "operationId": "generarPDFAnimales",
                "responses": {
                    "200": {
                        "description": "PDF generado exitosamente"
                    }
                }
            }
        },
        "/login": {
            "post": {
                "tags": [
                    "Autenticación"
                ],
                "summary": "Iniciar sesión",
                "description": "Iniciar sesión en la aplicación.",
                "operationId": "login",
                "requestBody": {
                    "description": "Credenciales de inicio de sesión",
                    "required": true,
                    "content": {
                        "application/json": {
                            "schema": {
                                "required": [
                                    "nombre_usuario",
                                    "contrasena"
                                ],
                                "properties": {
                                    "nombre_usuario": {
                                        "type": "string",
                                        "format": "string",
                                        "example": "usuarioejemplo"
                                    },
                                    "contrasena": {
                                        "type": "string",
                                        "format": "password",
                                        "example": "contrasenaejemplo"
                                    }
                                },
                                "type": "object"
                            }
                        }
                    }
                },
                "responses": {
                    "200": {
                        "description": "Inicio de sesión exitoso",
                        "content": {
                            "application/json": {
                                "schema": {
                                    "properties": {
                                        "access_token": {
                                            "type": "string",
                                            "format": "string"
                                        },
                                        "token_type": {
                                            "type": "string",
                                            "format": "string"
                                        },
                                        "expires_in": {
                                            "type": "integer",
                                            "format": "int"
                                        }
                                    },
                                    "type": "object"
                                }
                            }
                        }
                    },
                    "401": {
                        "description": "Credenciales incorrectas"
                    },
                    "422": {
                        "description": "Validación fallida",
                        "content": {
                            "application/json": {
                                "schema": {
                                    "properties": {
                                        "nombre_usuario": {
                                            "type": "array",
                                            "items": {
                                                "type": "string"
                                            }
                                        },
                                        "contrasena": {
                                            "type": "array",
                                            "items": {
                                                "type": "string"
                                            }
                                        }
                                    },
                                    "type": "object"
                                }
                            }
                        }
                    }
                }
            }
        },
        "/register": {
            "post": {
                "tags": [
                    "Registro"
                ],
                "summary": "Registrarse",
                "description": "Registrar una nueva cuenta de usuario.",
                "operationId": "register",
                "requestBody": {
                    "description": "Datos de registro de usuario",
                    "required": true,
                    "content": {
                        "application/json": {
                            "schema": {
                                "required": [
                                    "nombre",
                                    "nombre_usuario",
                                    "contrasena",
                                    "contrasena_confirmation",
                                    "apellido",
                                    "correo_electronico",
                                    "rol"
                                ],
                                "properties": {
                                    "nombre": {
                                        "type": "string",
                                        "format": "string",
                                        "example": "Nombre"
                                    },
                                    "nombre_usuario": {
                                        "type": "string",
                                        "format": "string",
                                        "example": "usuarioejemplo"
                                    },
                                    "contrasena": {
                                        "type": "string",
                                        "format": "password",
                                        "example": "contrasenaejemplo"
                                    },
                                    "contrasena_confirmation": {
                                        "type": "string",
                                        "format": "password",
                                        "example": "contrasenaejemplo"
                                    },
                                    "apellido": {
                                        "type": "string",
                                        "format": "string",
                                        "example": "Apellido"
                                    },
                                    "correo_electronico": {
                                        "type": "string",
                                        "format": "email",
                                        "example": "usuario@ejemplo.com"
                                    },
                                    "rol": {
                                        "type": "string",
                                        "format": "string",
                                        "example": "Rol"
                                    }
                                },
                                "type": "object"
                            }
                        }
                    }
                },
                "responses": {
                    "200": {
                        "description": "Usuario registrado exitosamente",
                        "content": {
                            "application/json": {
                                "schema": {
                                    "properties": {
                                        "message": {
                                            "type": "string",
                                            "format": "string"
                                        },
                                        "usuario": {
                                            "$ref": "#/components/schemas/usuario"
                                        },
                                        "token": {
                                            "type": "string",
                                            "format": "string"
                                        }
                                    },
                                    "type": "object"
                                }
                            }
                        }
                    },
                    "400": {
                        "description": "Error en el registro"
                    },
                    "422": {
                        "description": "Validación fallida",
                        "content": {
                            "application/json": {
                                "schema": {
                                    "properties": {
                                        "nombre": {
                                            "type": "array",
                                            "items": {
                                                "type": "string"
                                            }
                                        },
                                        "nombre_usuario": {
                                            "type": "array",
                                            "items": {
                                                "type": "string"
                                            }
                                        },
                                        "contrasena": {
                                            "type": "array",
                                            "items": {
                                                "type": "string"
                                            }
                                        },
                                        "apellido": {
                                            "type": "array",
                                            "items": {
                                                "type": "string"
                                            }
                                        },
                                        "correo_electronico": {
                                            "type": "array",
                                            "items": {
                                                "type": "string"
                                            }
                                        },
                                        "rol": {
                                            "type": "array",
                                            "items": {
                                                "type": "string"
                                            }
                                        }
                                    },
                                    "type": "object"
                                }
                            }
                        }
                    }
                }
            }
        },
        "/getaccount": {
            "get": {
                "tags": [
                    "usuario"
                ],
                "summary": "Obtener información del usuario autenticado",
                "description": "Obtiene información del usuario que ha iniciado sesión.",
                "operationId": "getaccount",
                "responses": {
                    "200": {
                        "description": "Información del usuario",
                        "content": {
                            "application/json": {
                                "schema": {
                                    "$ref": "#/components/schemas/usuario"
                                }
                            }
                        }
                    },
                    "401": {
                        "description": "No autorizado"
                    }
                },
                "security": [
                    {
                        "bearerAuth": []
                    }
                ]
            }
        },
        "/logout": {
            "post": {
                "tags": [
                    "Autenticación"
                ],
                "summary": "Cerrar sesión",
                "description": "Cerrar sesión del usuario autenticado.",
                "operationId": "logout",
                "responses": {
                    "200": {
                        "description": "Sesión cerrada exitosamente",
                        "content": {
                            "application/json": {
                                "schema": {
                                    "properties": {
                                        "message": {
                                            "type": "string",
                                            "format": "string",
                                            "example": "Sesión cerrada exitosamente"
                                        }
                                    },
                                    "type": "object"
                                }
                            }
                        }
                    },
                    "401": {
                        "description": "No autorizado"
                    }
                },
                "security": [
                    {
                        "bearerAuth": []
                    }
                ]
            }
        },
        "/estados-evento": {
            "get": {
                "tags": [
                    "Estados de Evento"
                ],
                "summary": "Obtener todos los estados de eventos",
                "description": "Recupera todos los estados de eventos de la base de datos.",
                "operationId": "indexEstEv",
                "responses": {
                    "200": {
                        "description": "Lista de estados de eventos",
                        "content": {
                            "application/json": {
                                "schema": {
                                    "type": "array",
                                    "items": {
                                        "$ref": "#/components/schemas/estado_evento"
                                    }
                                }
                            }
                        }
                    }
                }
            },
            "post": {
                "tags": [
                    "Estados de Evento"
                ],
                "summary": "Registrar un nuevo estado de evento",
                "description": "Crear un nuevo estado de evento con la información proporcionada.",
                "operationId": "storeEstEv",
                "requestBody": {
                    "description": "Datos del estado de evento",
                    "required": true,
                    "content": {
                        "application/json": {
                            "schema": {
                                "required": [
                                    "nombre"
                                ],
                                "properties": {
                                    "nombre": {
                                        "type": "string",
                                        "format": "string",
                                        "example": "Nombre del Estado"
                                    },
                                    "descripcion": {
                                        "type": "string",
                                        "format": "string",
                                        "example": "Descripción del Estado"
                                    }
                                },
                                "type": "object"
                            }
                        }
                    }
                },
                "responses": {
                    "201": {
                        "description": "Estado de evento registrado exitosamente",
                        "content": {
                            "application/json": {
                                "schema": {
                                    "$ref": "#/components/schemas/estado_evento"
                                }
                            }
                        }
                    },
                    "422": {
                        "description": "Validación fallida",
                        "content": {
                            "application/json": {
                                "schema": {
                                    "properties": {
                                        "error": {
                                            "type": "string",
                                            "example": "Error de validación"
                                        },
                                        "errors": {
                                            "type": "object"
                                        }
                                    },
                                    "type": "object"
                                }
                            }
                        }
                    }
                }
            }
        },
        "/estados-evento/{estado}": {
            "get": {
                "tags": [
                    "Estados de Evento"
                ],
                "summary": "Obtener información de un estado de evento",
                "description": "Obtiene información de un estado de evento por su ID.",
                "operationId": "showEstEv",
                "parameters": [
                    {
                        "name": "estado",
                        "in": "path",
                        "description": "ID del estado de evento",
                        "required": true,
                        "schema": {
                            "type": "integer"
                        }
                    }
                ],
                "responses": {
                    "200": {
                        "description": "Información del estado de evento",
                        "content": {
                            "application/json": {
                                "schema": {
                                    "$ref": "#/components/schemas/estado_evento"
                                }
                            }
                        }
                    },
                    "404": {
                        "description": "Estado de evento no encontrado",
                        "content": {
                            "application/json": {
                                "schema": {
                                    "properties": {
                                        "error": {
                                            "type": "string",
                                            "example": "Estado de evento no encontrado"
                                        }
                                    },
                                    "type": "object"
                                }
                            }
                        }
                    }
                }
            },
            "put": {
                "tags": [
                    "Estados de Evento"
                ],
                "summary": "Actualizar un estado de evento",
                "description": "Actualiza un estado de evento existente con la información proporcionada.",
                "operationId": "updateEstEv",
                "parameters": [
                    {
                        "name": "estado",
                        "in": "path",
                        "description": "ID del estado de evento",
                        "required": true,
                        "schema": {
                            "type": "integer"
                        }
                    }
                ],
                "requestBody": {
                    "description": "Datos actualizados del estado de evento",
                    "required": true,
                    "content": {
                        "application/json": {
                            "schema": {
                                "required": [
                                    "nombre"
                                ],
                                "properties": {
                                    "nombre": {
                                        "type": "string",
                                        "format": "string",
                                        "example": "Nuevo Nombre del Estado"
                                    },
                                    "descripcion": {
                                        "type": "string",
                                        "format": "string",
                                        "example": "Nueva Descripción del Estado"
                                    }
                                },
                                "type": "object"
                            }
                        }
                    }
                },
                "responses": {
                    "200": {
                        "description": "Estado de evento actualizado exitosamente",
                        "content": {
                            "application/json": {
                                "schema": {
                                    "$ref": "#/components/schemas/estado_evento"
                                }
                            }
                        }
                    },
                    "404": {
                        "description": "Estado de evento no encontrado",
                        "content": {
                            "application/json": {
                                "schema": {
                                    "properties": {
                                        "error": {
                                            "type": "string",
                                            "example": "Estado de evento no encontrado"
                                        }
                                    },
                                    "type": "object"
                                }
                            }
                        }
                    },
                    "422": {
                        "description": "Validación fallida",
                        "content": {
                            "application/json": {
                                "schema": {
                                    "properties": {
                                        "error": {
                                            "type": "string",
                                            "example": "Error de validación"
                                        },
                                        "errors": {
                                            "type": "object"
                                        }
                                    },
                                    "type": "object"
                                }
                            }
                        }
                    }
                }
            },
            "delete": {
                "tags": [
                    "Estados de Evento"
                ],
                "summary": "Eliminar un estado de evento",
                "description": "Elimina un estado de evento existente por su ID.",
                "operationId": "destroyEstEv",
                "parameters": [
                    {
                        "name": "estado",
                        "in": "path",
                        "description": "ID del estado de evento",
                        "required": true,
                        "schema": {
                            "type": "integer"
                        }
                    }
                ],
                "responses": {
                    "204": {
                        "description": "Estado de evento eliminado exitosamente"
                    },
                    "404": {
                        "description": "Estado de evento no encontrado",
                        "content": {
                            "application/json": {
                                "schema": {
                                    "properties": {
                                        "error": {
                                            "type": "string",
                                            "example": "Estado de evento no encontrado"
                                        }
                                    },
                                    "type": "object"
                                }
                            }
                        }
                    }
                }
            }
        },
        "/movimientos-animales": {
            "get": {
                "tags": [
                    "MovimientosAnimales"
                ],
                "summary": "Obtener todos los movimientos de animales",
                "description": "Recupera todos los movimientos de animales de la base de datos.",
                "operationId": "indexMovimientosAnimales",
                "responses": {
                    "200": {
                        "description": "Lista de movimientos de animales",
                        "content": {
                            "application/json": {
                                "schema": {
                                    "type": "array",
                                    "items": {
                                        "$ref": "#/components/schemas/movimientosAnimales"
                                    }
                                }
                            }
                        }
                    }
                }
            },
            "post": {
                "tags": [
                    "MovimientosAnimales"
                ],
                "summary": "Registrar un nuevo movimiento de animal",
                "description": "Crea un nuevo movimiento de animal con la información proporcionada.",
                "operationId": "storeMovimientoAnimal",
                "requestBody": {
                    "description": "Datos del movimiento de animal",
                    "required": true,
                    "content": {
                        "application/json": {
                            "schema": {
                                "required": [
                                    "id_solicitud",
                                    "id_rescate",
                                    "id_usuario",
                                    "fecha_movimiento"
                                ],
                                "properties": {
                                    "id_solicitud": {
                                        "type": "integer",
                                        "format": "int",
                                        "example": 1
                                    },
                                    "id_rescate": {
                                        "type": "integer",
                                        "format": "int",
                                        "example": 2
                                    },
                                    "id_usuario": {
                                        "type": "integer",
                                        "format": "int",
                                        "example": 3
                                    },
                                    "fecha_movimiento": {
                                        "type": "string",
                                        "format": "date",
                                        "example": "2023-01-01"
                                    }
                                },
                                "type": "object"
                            }
                        }
                    }
                },
                "responses": {
                    "201": {
                        "description": "Movimiento de animal registrado exitosamente",
                        "content": {
                            "application/json": {
                                "schema": {
                                    "$ref": "#/components/schemas/movimientosAnimales"
                                }
                            }
                        }
                    },
                    "422": {
                        "description": "Validación fallida",
                        "content": {
                            "application/json": {
                                "schema": {
                                    "properties": {
                                        "error": {
                                            "type": "string",
                                            "example": "Error de validación"
                                        },
                                        "errors": {
                                            "type": "object"
                                        }
                                    },
                                    "type": "object"
                                }
                            }
                        }
                    }
                }
            }
        },
        "/movimientos-animales/{id}": {
            "put": {
                "tags": [
                    "MovimientosAnimales"
                ],
                "summary": "Actualizar un movimiento de animal",
                "description": "Actualiza un movimiento de animal existente por su ID con la información proporcionada.",
                "operationId": "updateMovimientoAnimal",
                "parameters": [
                    {
                        "name": "id",
                        "in": "path",
                        "description": "ID del movimiento de animal",
                        "required": true,
                        "schema": {
                            "type": "integer"
                        }
                    }
                ],
                "requestBody": {
                    "description": "Datos actualizados del movimiento de animal",
                    "required": true,
                    "content": {
                        "application/json": {
                            "schema": {
                                "required": [
                                    "id_solicitud",
                                    "id_rescate",
                                    "id_usuario",
                                    "fecha_movimiento"
                                ],
                                "properties": {
                                    "id_solicitud": {
                                        "type": "integer",
                                        "format": "int",
                                        "example": 1
                                    },
                                    "id_rescate": {
                                        "type": "integer",
                                        "format": "int",
                                        "example": 2
                                    },
                                    "id_usuario": {
                                        "type": "integer",
                                        "format": "int",
                                        "example": 3
                                    },
                                    "fecha_movimiento": {
                                        "type": "string",
                                        "format": "date",
                                        "example": "2023-01-01"
                                    }
                                },
                                "type": "object"
                            }
                        }
                    }
                },
                "responses": {
                    "200": {
                        "description": "Movimiento de animal actualizado exitosamente",
                        "content": {
                            "application/json": {
                                "schema": {
                                    "$ref": "#/components/schemas/movimientosAnimales"
                                }
                            }
                        }
                    },
                    "404": {
                        "description": "Movimiento de animal no encontrado",
                        "content": {
                            "application/json": {
                                "schema": {
                                    "properties": {
                                        "error": {
                                            "type": "string",
                                            "example": "Movimiento de animal no encontrado"
                                        }
                                    },
                                    "type": "object"
                                }
                            }
                        }
                    },
                    "422": {
                        "description": "Validación fallida",
                        "content": {
                            "application/json": {
                                "schema": {
                                    "properties": {
                                        "error": {
                                            "type": "string",
                                            "example": "Error de validación"
                                        },
                                        "errors": {
                                            "type": "object"
                                        }
                                    },
                                    "type": "object"
                                }
                            }
                        }
                    }
                }
            },
            "delete": {
                "tags": [
                    "MovimientosAnimales"
                ],
                "summary": "Eliminar un movimiento de animal",
                "description": "Elimina un movimiento de animal existente por su ID.",
                "operationId": "deleteMovimientoAnimal",
                "parameters": [
                    {
                        "name": "id",
                        "in": "path",
                        "description": "ID del movimiento de animal",
                        "required": true,
                        "schema": {
                            "type": "integer"
                        }
                    }
                ],
                "responses": {
                    "204": {
                        "description": "Movimiento de animal eliminado exitosamente"
                    },
                    "404": {
                        "description": "Movimiento de animal no encontrado",
                        "content": {
                            "application/json": {
                                "schema": {
                                    "properties": {
                                        "error": {
                                            "type": "string",
                                            "example": "Movimiento de animal no encontrado"
                                        }
                                    },
                                    "type": "object"
                                }
                            }
                        }
                    }
                }
            }
        },
        "/rescates": {
            "get": {
                "tags": [
                    "Rescates"
                ],
                "summary": "Obtener todos los rescates",
                "description": "Recupera todos los rescates de la base de datos.",
                "operationId": "indexRescates",
                "responses": {
                    "200": {
                        "description": "Lista de rescates",
                        "content": {
                            "application/json": {
                                "schema": {
                                    "type": "array",
                                    "items": {
                                        "$ref": "#/components/schemas/rescate"
                                    }
                                }
                            }
                        }
                    }
                }
            },
            "post": {
                "tags": [
                    "Rescates"
                ],
                "summary": "Registrar un nuevo rescate",
                "description": "Crear un nuevo rescate con la información proporcionada.",
                "operationId": "storeResc",
                "requestBody": {
                    "description": "Datos del rescate",
                    "required": true,
                    "content": {
                        "application/json": {
                            "schema": {
                                "required": [
                                    "id_usuario",
                                    "direccion",
                                    "estado",
                                    "fecha_rescate",
                                    "id_animal"
                                ],
                                "properties": {
                                    "id_usuario": {
                                        "type": "integer",
                                        "format": "int",
                                        "example": 1
                                    },
                                    "direccion": {
                                        "type": "string",
                                        "format": "string",
                                        "example": "Dirección del rescate"
                                    },
                                    "estado": {
                                        "type": "string",
                                        "format": "string",
                                        "example": "En curso"
                                    },
                                    "fecha_rescate": {
                                        "type": "string",
                                        "format": "date",
                                        "example": "2023-11-19"
                                    },
                                    "informacion_adicional": {
                                        "type": "string",
                                        "format": "string"
                                    },
                                    "id_animal": {
                                        "type": "integer",
                                        "format": "int",
                                        "example": 1
                                    }
                                },
                                "type": "object"
                            }
                        }
                    }
                },
                "responses": {
                    "201": {
                        "description": "Rescate registrado exitosamente",
                        "content": {
                            "application/json": {
                                "schema": {
                                    "$ref": "#/components/schemas/rescate"
                                }
                            }
                        }
                    },
                    "422": {
                        "description": "Validación fallida",
                        "content": {
                            "application/json": {
                                "schema": {
                                    "properties": {
                                        "error": {
                                            "type": "string",
                                            "example": "Error de validación"
                                        },
                                        "errors": {
                                            "type": "object"
                                        }
                                    },
                                    "type": "object"
                                }
                            }
                        }
                    }
                }
            }
        },
        "/rescates/store2": {
            "post": {
                "tags": [
                    "Rescates"
                ],
                "summary": "Registrar un nuevo rescate con información detallada del animal",
                "description": "Crear un nuevo rescate con información detallada del animal proporcionada.",
                "operationId": "store2resc",
                "requestBody": {
                    "description": "Datos del rescate con información detallada del animal",
                    "required": true,
                    "content": {
                        "application/json": {
                            "schema": {
                                "required": [
                                    "id_usuario",
                                    "direccion",
                                    "estado",
                                    "fecha_rescate",
                                    "id_animal"
                                ],
                                "properties": {
                                    "id_usuario": {
                                        "type": "integer",
                                        "format": "int",
                                        "example": 1
                                    },
                                    "direccion": {
                                        "type": "string",
                                        "format": "string",
                                        "example": "Dirección del rescate"
                                    },
                                    "estado": {
                                        "type": "string",
                                        "format": "string",
                                        "example": "En curso"
                                    },
                                    "fecha_rescate": {
                                        "type": "string",
                                        "format": "date",
                                        "example": "2023-11-19"
                                    },
                                    "informacion_adicional": {
                                        "type": "string",
                                        "format": "string"
                                    },
                                    "id_animal": {
                                        "required": [
                                            "nombre",
                                            "especie"
                                        ],
                                        "properties": {
                                            "nombre": {
                                                "type": "string",
                                                "format": "string",
                                                "example": "Nombre del animal"
                                            },
                                            "especie": {
                                                "type": "string",
                                                "format": "string",
                                                "example": "Especie del animal"
                                            },
                                            "tamano": {
                                                "type": "string",
                                                "format": "string",
                                                "example": "tamano del animal"
                                            },
                                            "edad": {
                                                "type": "integer",
                                                "format": "int",
                                                "example": 3
                                            },
                                            "descripcion": {
                                                "type": "string",
                                                "format": "string",
                                                "example": "Descripción del animal"
                                            }
                                        },
                                        "type": "object"
                                    }
                                },
                                "type": "object"
                            }
                        }
                    }
                },
                "responses": {
                    "201": {
                        "description": "Rescate registrado exitosamente",
                        "content": {
                            "application/json": {
                                "schema": {
                                    "$ref": "#/components/schemas/rescate"
                                }
                            }
                        }
                    },
                    "422": {
                        "description": "Validación fallida",
                        "content": {
                            "application/json": {
                                "schema": {
                                    "properties": {
                                        "error": {
                                            "type": "string",
                                            "example": "Error de validación"
                                        },
                                        "errors": {
                                            "type": "object"
                                        }
                                    },
                                    "type": "object"
                                }
                            }
                        }
                    }
                }
            }
        },
        "/rescates/{id}": {
            "get": {
                "tags": [
                    "Rescates"
                ],
                "summary": "Obtener información de un rescate",
                "description": "Obtiene información de un rescate por su ID.",
                "operationId": "showResc",
                "parameters": [
                    {
                        "name": "id",
                        "in": "path",
                        "description": "ID del rescate",
                        "required": true,
                        "schema": {
                            "type": "integer"
                        }
                    }
                ],
                "responses": {
                    "200": {
                        "description": "Información del rescate",
                        "content": {
                            "application/json": {
                                "schema": {
                                    "$ref": "#/components/schemas/rescate"
                                }
                            }
                        }
                    },
                    "404": {
                        "description": "Rescate no encontrado",
                        "content": {
                            "application/json": {
                                "schema": {
                                    "properties": {
                                        "error": {
                                            "type": "string",
                                            "example": "Rescate no encontrado"
                                        }
                                    },
                                    "type": "object"
                                }
                            }
                        }
                    }
                }
            },
            "put": {
                "tags": [
                    "Rescates"
                ],
                "summary": "Actualizar un rescate",
                "description": "Actualizar la información de un rescate por su ID.",
                "operationId": "update",
                "parameters": [
                    {
                        "name": "id",
                        "in": "path",
                        "description": "ID del rescate",
                        "required": true,
                        "schema": {
                            "type": "integer"
                        }
                    }
                ],
                "requestBody": {
                    "description": "Datos actualizados del rescate",
                    "required": true,
                    "content": {
                        "application/json": {
                            "schema": {
                                "required": [
                                    "id_usuario",
                                    "direccion",
                                    "estado",
                                    "fecha_rescate",
                                    "id_animal"
                                ],
                                "properties": {
                                    "id_usuario": {
                                        "type": "integer",
                                        "format": "int",
                                        "example": 1
                                    },
                                    "direccion": {
                                        "type": "string",
                                        "format": "string",
                                        "example": "Nueva dirección del rescate"
                                    },
                                    "estado": {
                                        "type": "string",
                                        "format": "string",
                                        "example": "Completado"
                                    },
                                    "fecha_rescate": {
                                        "type": "string",
                                        "format": "date",
                                        "example": "2023-11-20"
                                    },
                                    "informacion_adicional": {
                                        "type": "string",
                                        "format": "string",
                                        "example": "Nueva información adicional"
                                    },
                                    "id_animal": {
                                        "type": "integer",
                                        "format": "int",
                                        "example": 2
                                    }
                                },
                                "type": "object"
                            }
                        }
                    }
                },
                "responses": {
                    "200": {
                        "description": "Rescate actualizado exitosamente",
                        "content": {
                            "application/json": {
                                "schema": {
                                    "$ref": "#/components/schemas/rescate"
                                }
                            }
                        }
                    },
                    "404": {
                        "description": "Rescate no encontrado",
                        "content": {
                            "application/json": {
                                "schema": {
                                    "properties": {
                                        "error": {
                                            "type": "string",
                                            "example": "Rescate no encontrado"
                                        }
                                    },
                                    "type": "object"
                                }
                            }
                        }
                    },
                    "422": {
                        "description": "Validación fallida",
                        "content": {
                            "application/json": {
                                "schema": {
                                    "properties": {
                                        "error": {
                                            "type": "string",
                                            "example": "Error de validación"
                                        },
                                        "errors": {
                                            "type": "object"
                                        }
                                    },
                                    "type": "object"
                                }
                            }
                        }
                    }
                }
            },
            "delete": {
                "tags": [
                    "Rescates"
                ],
                "summary": "Eliminar un rescate",
                "description": "Elimina un rescate existente por su ID.",
                "operationId": "deleteRescate",
                "parameters": [
                    {
                        "name": "id",
                        "in": "path",
                        "description": "ID del rescate",
                        "required": true,
                        "schema": {
                            "type": "integer"
                        }
                    }
                ],
                "responses": {
                    "204": {
                        "description": "Rescate eliminado exitosamente"
                    },
                    "404": {
                        "description": "Rescate no encontrado",
                        "content": {
                            "application/json": {
                                "schema": {
                                    "properties": {
                                        "error": {
                                            "type": "string",
                                            "example": "Rescate no encontrado"
                                        }
                                    },
                                    "type": "object"
                                }
                            }
                        }
                    }
                }
            }
        },
        "/solicitudes": {
            "get": {
                "tags": [
                    "Solicitudes"
                ],
                "summary": "Obtener todas las solicitudes de adopción",
                "description": "Recupera todas las solicitudes de adopción de la base de datos.",
                "operationId": "indexSolicitudes",
                "responses": {
                    "200": {
                        "description": "Lista de solicitudes de adopción",
                        "content": {
                            "application/json": {
                                "schema": {
                                    "type": "array",
                                    "items": {
                                        "$ref": "#/components/schemas/solicitudDeAdopcion"
                                    }
                                }
                            }
                        }
                    }
                }
            },
            "post": {
                "tags": [
                    "Solicitudes"
                ],
                "summary": "Registrar una nueva solicitud de adopción",
                "description": "Crear una nueva solicitud de adopción con la información proporcionada.",
                "operationId": "storeSolicitud",
                "requestBody": {
                    "description": "Datos de la solicitud de adopción",
                    "required": true,
                    "content": {
                        "application/json": {
                            "schema": {
                                "required": [
                                    "id_del_usuario",
                                    "id_del_adoptante",
                                    "id_del_animal",
                                    "fecha_solicitud",
                                    "estado"
                                ],
                                "properties": {
                                    "id_del_usuario": {
                                        "type": "integer",
                                        "format": "int",
                                        "example": 1
                                    },
                                    "id_del_adoptante": {
                                        "type": "integer",
                                        "format": "int",
                                        "example": 2
                                    },
                                    "id_del_animal": {
                                        "type": "integer",
                                        "format": "int",
                                        "example": 3
                                    },
                                    "fecha_solicitud": {
                                        "type": "string",
                                        "format": "date",
                                        "example": "2023-01-01"
                                    },
                                    "datos_adicionales": {
                                        "type": "string",
                                        "format": "string",
                                        "example": "Información adicional"
                                    },
                                    "estado": {
                                        "type": "boolean",
                                        "format": "boolean",
                                        "example": true
                                    }
                                },
                                "type": "object"
                            }
                        }
                    }
                },
                "responses": {
                    "201": {
                        "description": "Solicitud de adopción registrada exitosamente",
                        "content": {
                            "application/json": {
                                "schema": {
                                    "$ref": "#/components/schemas/solicitudDeAdopcion"
                                }
                            }
                        }
                    },
                    "422": {
                        "description": "Validación fallida",
                        "content": {
                            "application/json": {
                                "schema": {
                                    "properties": {
                                        "error": {
                                            "type": "string",
                                            "example": "Error de validación"
                                        },
                                        "errors": {
                                            "type": "object"
                                        }
                                    },
                                    "type": "object"
                                }
                            }
                        }
                    }
                }
            }
        },
        "/solicitudes/{id}": {
            "get": {
                "tags": [
                    "Solicitudes"
                ],
                "summary": "Obtener información de una solicitud de adopción",
                "description": "Obtiene información de una solicitud de adopción por su ID.",
                "operationId": "showSolicitud",
                "parameters": [
                    {
                        "name": "id",
                        "in": "path",
                        "description": "ID de la solicitud de adopción",
                        "required": true,
                        "schema": {
                            "type": "integer"
                        }
                    }
                ],
                "responses": {
                    "200": {
                        "description": "Información de la solicitud de adopción",
                        "content": {
                            "application/json": {
                                "schema": {
                                    "$ref": "#/components/schemas/solicitudDeAdopcion"
                                }
                            }
                        }
                    },
                    "404": {
                        "description": "Solicitud de adopción no encontrada",
                        "content": {
                            "application/json": {
                                "schema": {
                                    "properties": {
                                        "error": {
                                            "type": "string",
                                            "example": "Solicitud de adopción no encontrada"
                                        }
                                    },
                                    "type": "object"
                                }
                            }
                        }
                    }
                }
            },
            "put": {
                "tags": [
                    "Solicitudes"
                ],
                "summary": "Actualizar una solicitud de adopción",
                "description": "Actualiza una solicitud de adopción existente por su ID con la información proporcionada.",
                "operationId": "updateSolicitud",
                "parameters": [
                    {
                        "name": "id",
                        "in": "path",
                        "description": "ID de la solicitud de adopción",
                        "required": true,
                        "schema": {
                            "type": "integer"
                        }
                    }
                ],
                "requestBody": {
                    "description": "Datos actualizados de la solicitud de adopción",
                    "required": true,
                    "content": {
                        "application/json": {
                            "schema": {
                                "required": [
                                    "id_del_usuario",
                                    "id_del_adoptante",
                                    "id_del_animal",
                                    "fecha_solicitud",
                                    "estado"
                                ],
                                "properties": {
                                    "id_del_usuario": {
                                        "type": "integer",
                                        "format": "int",
                                        "example": 1
                                    },
                                    "id_del_adoptante": {
                                        "type": "integer",
                                        "format": "int",
                                        "example": 2
                                    },
                                    "id_del_animal": {
                                        "type": "integer",
                                        "format": "int",
                                        "example": 3
                                    },
                                    "fecha_solicitud": {
                                        "type": "string",
                                        "format": "date",
                                        "example": "2023-01-01"
                                    },
                                    "datos_adicionales": {
                                        "type": "string",
                                        "format": "string",
                                        "example": "Información adicional actualizada"
                                    },
                                    "estado": {
                                        "type": "boolean",
                                        "format": "boolean",
                                        "example": true
                                    }
                                },
                                "type": "object"
                            }
                        }
                    }
                },
                "responses": {
                    "200": {
                        "description": "Solicitud de adopción actualizada exitosamente",
                        "content": {
                            "application/json": {
                                "schema": {
                                    "$ref": "#/components/schemas/solicitudDeAdopcion"
                                }
                            }
                        }
                    },
                    "404": {
                        "description": "Solicitud de adopción no encontrada",
                        "content": {
                            "application/json": {
                                "schema": {
                                    "properties": {
                                        "error": {
                                            "type": "string",
                                            "example": "Solicitud de adopción no encontrada"
                                        }
                                    },
                                    "type": "object"
                                }
                            }
                        }
                    }
                }
            }
        },
        "/usuarios": {
            "get": {
                "tags": [
                    "Usuarios"
                ],
                "summary": "Obtener todos los usuarios",
                "description": "Obtiene la lista de todos los usuarios en la base de datos",
                "operationId": "index",
                "responses": {
                    "200": {
                        "description": "Lista de usuarios",
                        "content": {
                            "application/json": {
                                "schema": {
                                    "type": "array",
                                    "items": {
                                        "$ref": "#/components/schemas/usuario"
                                    }
                                }
                            }
                        }
                    }
                },
                "security": [
                    {
                        "api_key": []
                    }
                ]
            }
        },
        "/generarPdf": {
            "get": {
                "tags": [
                    "Usuarios"
                ],
                "summary": "Generar PDF de usuarios",
                "description": "Genera un archivo PDF que contiene la lista de usuarios",
                "operationId": "generarPDF",
                "responses": {
                    "200": {
                        "description": "PDF generado exitosamente"
                    }
                },
                "security": [
                    {
                        "api_key": []
                    }
                ]
            }
        }
    },
    "components": {
        "schemas": {
            "adoptante": {
                "title": "adoptante",
                "properties": {
                    "id": {
                        "type": "integer"
                    },
                    "nombre": {
                        "type": "string"
                    },
                    "apellido": {
                        "type": "string"
                    },
                    "correo_electronico": {
                        "type": "string"
                    },
                    "telefono": {
                        "type": "string"
                    },
                    "direccion": {
                        "type": "string"
                    },
                    "ocupacion": {
                        "type": "string"
                    }
                },
                "type": "object"
            },
            "animal": {
                "title": "animal",
                "properties": {
                    "id": {
                        "type": "integer"
                    },
                    "nombre": {
                        "type": "string"
                    },
                    "especie": {
                        "type": "string"
                    },
                    "raza": {
                        "type": "string"
                    },
                    "edad": {
                        "type": "integer"
                    },
                    "descripcion": {
                        "type": "string"
                    }
                },
                "type": "object"
            },
            "usuario": {
                "title": "usuario",
                "properties": {
                    "id": {
                        "type": "integer"
                    },
                    "apellido": {
                        "type": "string"
                    },
                    "nombre_usuario": {
                        "type": "string"
                    },
                    "contrasena": {
                        "type": "string"
                    },
                    "correo_electronico": {
                        "type": "string"
                    },
                    "rol": {
                        "type": "string"
                    }
                },
                "type": "object"
            },
            "estado_evento": {
                "title": "estado_evento",
                "properties": {
                    "id": {
                        "type": "integer"
                    },
                    "nombre": {
                        "type": "string"
                    },
                    "descripcion": {
                        "type": "string"
                    }
                },
                "type": "object"
            },
            "evento_recaudacion": {
                "title": "Evento de Recaudación",
                "properties": {
                    "id": {
                        "type": "integer"
                    },
                    "nombre_del_evento": {
                        "type": "string"
                    },
                    "fecha": {
                        "type": "string",
                        "format": "date"
                    },
                    "ubicacion": {
                        "type": "string"
                    },
                    "descripcion": {
                        "type": "string"
                    },
                    "id_estado": {
                        "type": "integer"
                    },
                    "id_del_usuario": {
                        "type": "integer"
                    },
                    "id_tipo_evento": {
                        "type": "integer"
                    },
                    "created_at": {
                        "type": "string",
                        "format": "date-time"
                    },
                    "updated_at": {
                        "type": "string",
                        "format": "date-time"
                    },
                    "estadoEvento": {
                        "$ref": "#/components/schemas/estado_evento"
                    },
                    "usuario": {
                        "$ref": "#/components/schemas/usuario"
                    },
                    "tipoEvento": {
                        "$ref": "#/components/schemas/tipo_evento"
                    }
                },
                "type": "object"
            },
            "movimientosAnimales": {
                "title": "movimientosAnimales",
                "properties": {
                    "id": {
                        "type": "integer"
                    },
                    "id_solicitud": {
                        "type": "integer"
                    },
                    "id_rescate": {
                        "type": "integer"
                    },
                    "id_usuario": {
                        "type": "integer"
                    },
                    "fecha_movimiento": {
                        "type": "string",
                        "format": "date"
                    }
                },
                "type": "object"
            },
            "rescate": {
                "title": "rescate",
                "properties": {
                    "id": {
                        "type": "integer"
                    },
                    "id_usuario": {
                        "type": "integer"
                    },
                    "direccion": {
                        "type": "string"
                    },
                    "estado": {
                        "type": "string"
                    },
                    "fecha_rescate": {
                        "type": "string",
                        "format": "date"
                    },
                    "informacion_adicional": {
                        "type": "string"
                    },
                    "id_animal": {
                        "type": "integer"
                    }
                },
                "type": "object"
            },
            "solicitudDeAdopcion": {
                "title": "solicitudDeAdopcion",
                "properties": {
                    "id": {
                        "type": "integer"
                    },
                    "id_del_usuario": {
                        "type": "integer"
                    },
                    "id_del_adoptante": {
                        "type": "integer"
                    },
                    "id_del_animal": {
                        "type": "integer"
                    },
                    "fecha_solicitud": {
                        "type": "string",
                        "format": "date"
                    },
                    "datos_adicionales": {
                        "type": "string"
                    },
                    "estado": {
                        "type": "boolean"
                    }
                },
                "type": "object"
            },
            "tipo_evento": {
                "title": "Tipo de Evento",
                "properties": {
                    "id": {
                        "type": "integer"
                    },
                    "descripcion": {
                        "type": "string"
                    },
                    "created_at": {
                        "type": "string",
                        "format": "date-time"
                    },
                    "updated_at": {
                        "type": "string",
                        "format": "date-time"
                    }
                },
                "type": "object"
            }
        }
    }
}